Hbase097ZhongwenWendang/README.md
Hbase097ZhongwenWendang/__init__.py
Hbase097ZhongwenWendang/__main__.py
Hbase097ZhongwenWendang/file.epub
Hbase097ZhongwenWendang/index.html
Hbase097ZhongwenWendang/css/__init__.py
Hbase097ZhongwenWendang/css/annotations.css
Hbase097ZhongwenWendang/css/main.css
Hbase097ZhongwenWendang/css/normalize.css
Hbase097ZhongwenWendang/css/popup.css
Hbase097ZhongwenWendang/font/__init__.py
Hbase097ZhongwenWendang/font/fontello.eot
Hbase097ZhongwenWendang/font/fontello.svg
Hbase097ZhongwenWendang/font/fontello.ttf
Hbase097ZhongwenWendang/font/fontello.woff
Hbase097ZhongwenWendang/img/__init__.py
Hbase097ZhongwenWendang/img/annotator-glyph-sprite.png
Hbase097ZhongwenWendang/img/annotator-icon-sprite.png
Hbase097ZhongwenWendang/img/apple-touch-icon.png
Hbase097ZhongwenWendang/img/cancelfullscreen.png
Hbase097ZhongwenWendang/img/close.png
Hbase097ZhongwenWendang/img/fullscreen.png
Hbase097ZhongwenWendang/img/loader.gif
Hbase097ZhongwenWendang/img/menu-icon.png
Hbase097ZhongwenWendang/img/save.png
Hbase097ZhongwenWendang/img/saved.png
Hbase097ZhongwenWendang/img/settings-s.png
Hbase097ZhongwenWendang/img/settings.png
Hbase097ZhongwenWendang/img/star.png
Hbase097ZhongwenWendang/js/__init__.py
Hbase097ZhongwenWendang/js/epub.js
Hbase097ZhongwenWendang/js/epub.min.js
Hbase097ZhongwenWendang/js/epub.min.map
Hbase097ZhongwenWendang/js/hooks.min.js
Hbase097ZhongwenWendang/js/hooks.min.map
Hbase097ZhongwenWendang/js/reader.js
Hbase097ZhongwenWendang/js/reader.js.map
Hbase097ZhongwenWendang/js/reader.min.js
Hbase097ZhongwenWendang/js/reader.min.map
Hbase097ZhongwenWendang/js/hooks/__init__.py
Hbase097ZhongwenWendang/js/hooks/extensions/__init__.py
Hbase097ZhongwenWendang/js/hooks/extensions/highlight.js
Hbase097ZhongwenWendang/js/libs/__init__.py
Hbase097ZhongwenWendang/js/libs/jquery.min.js
Hbase097ZhongwenWendang/js/libs/localforage.min.js
Hbase097ZhongwenWendang/js/libs/screenfull.js
Hbase097ZhongwenWendang/js/libs/screenfull.min.js
hbase_0_97_zhongwen_wendang-2024.3.2.0.dist-info/METADATA
hbase_0_97_zhongwen_wendang-2024.3.2.0.dist-info/WHEEL
hbase_0_97_zhongwen_wendang-2024.3.2.0.dist-info/entry_points.txt
hbase_0_97_zhongwen_wendang-2024.3.2.0.dist-info/top_level.txt
hbase_0_97_zhongwen_wendang-2024.3.2.0.dist-info/RECORD
